[
  {
    "time": "2021-05-06T13:02:00.200Z",
    "name": "Michael Lee",
    "city": "Miami",
    "age": 49,
    "salary": 64612,
    "occupation": "DevOps Engineer",
    "marital_status": "Single"
  },
  {
    "time": "2021-05-06T13:02:00.200Z",
    "name": "Laura Kim",
    "city": "Los Angeles",
    "age": 34,
    "salary": 77970,
    "occupation": "Marketing Specialist",
    "marital_status": "Married"
  },
  {
    "time": "2021-05-06T13:02:00.200Z",
    "name": "Robert Brown",
    "city": "New York",
    "age": 22,
    "salary": 61234,
    "occupation": "Financial Analyst",
    "marital_status": "Married"
  },
  {
    "time": "2021-05-06T13:02:00.200Z",
    "name": "Sophia Martinez",
    "city": "Chicago",
    "age": 43,
    "salary": 64518,
    "occupation": "Product Manager",
    "marital_status": "Married"
  },
  {
    "time": "2021-05-06T13:02:00.200Z",
    "name": "Michael Lee",
    "city": "Seattle",
    "age": 24,
    "salary": 69205,
    "occupation": "Financial Analyst",
    "marital_status": "Married"
  },
  {
    "time": "2021-05-06T13:02:00.200Z",
    "name": "Michael Lee",
    "city": "Phoenix",
    "age": 49,
    "salary": 51180,
    "occupation": "Software Engineer",
    "marital_status": "Married"
  },
  {
    "time": "2021-05-06T13:02:00.200Z",
    "name": "Robert Brown",
    "city": "Phoenix",
    "age": 29,
    "salary": 56076,
    "occupation": "Data Scientist",
    "marital_status": "Single"
  },
  {
    "time": "2021-05-06T13:02:00.200Z",
    "name": "Michael Lee",
    "city": "Phoenix",
    "age": 23,
    "salary": 77802,
    "occupation": "Marketing Specialist",
    "marital_status": "Single"
  },
  {
    "time": "2021-05-06T13:02:00.200Z",
    "name": "Emily Davis",
    "city": "San Francisco",
    "age": 59,
    "salary": 70956,
    "occupation": "Data Scientist",
    "marital_status": "Single"
  },
  {
    "time": "2021-05-06T13:02:00.200Z",
    "name": "James Wilson",
    "city": "Miami",
    "age": 36,
    "salary": 60295,
    "occupation": "Product Manager",
    "marital_status": "Single"
  },
  {
    "time": "2021-05-06T13:02:00.200Z",
    "name": "James Wilson",
    "city": "Chicago",
    "age": 23,
    "salary": 64359,
    "occupation": "DevOps Engineer",
    "marital_status": "Married"
  },
  {
    "time": "2021-05-06T13:02:00.200Z",
    "name": "Alice Johnson",
    "city": "Chicago",
    "age": 40,
    "salary": 60494,
    "occupation": "Product Manager",
    "marital_status": "Married"
  },
  {
    "time": "2021-05-06T13:02:00.200Z",
    "name": "Michael Lee",
    "city": "Los Angeles",
    "age": 56,
    "salary": 55371,
    "occupation": "Financial Analyst",
    "marital_status": "Married"
  },
  {
    "time": "2021-05-06T13:02:00.200Z",
    "name": "Robert Brown",
    "city": "Miami",
    "age": 29,
    "salary": 58036,
    "occupation": "DevOps Engineer",
    "marital_status": "Single"
  },
  {
    "time": "2021-05-06T13:02:00.200Z",
    "name": "Laura Kim",
    "city": "Seattle",
    "age": 58,
    "salary": 81931,
    "occupation": "Data Scientist",
    "marital_status": "Single"
  },
  {
    "time": "2021-05-06T13:02:00.200Z",
    "name": "Robert Brown",
    "city": "Phoenix",
    "age": 22,
    "salary": 60857,
    "occupation": "Marketing Specialist",
    "marital_status": "Single"
  },
  {
    "time": "2021-05-06T13:02:00.200Z",
    "name": "Laura Kim",
    "city": "Phoenix",
    "age": 35,
    "salary": 74496,
    "occupation": "Graphic Designer",
    "marital_status": "Single"
  },
  {
    "time": "2021-05-06T13:02:00.200Z",
    "name": "Robert Brown",
    "city": "Houston",
    "age": 26,
    "salary": 63824,
    "occupation": "Financial Analyst",
    "marital_status": "Married"
  },
  {
    "time": "2021-05-06T13:02:00.200Z",
    "name": "Michael Lee",
    "city": "Boston",
    "age": 30,
    "salary": 71917,
    "occupation": "Graphic Designer",
    "marital_status": "Married"
  },
  {
    "time": "2021-05-06T13:02:00.200Z",
    "name": "Robert Brown",
    "city": "San Francisco",
    "age": 29,
    "salary": 69503,
    "occupation": "Financial Analyst",
    "marital_status": "Single"
  },
  {
    "time": "2021-05-06T13:02:00.200Z",
    "name": "Emily Davis",
    "city": "Boston",
    "age": 26,
    "salary": 67844,
    "occupation": "Graphic Designer",
    "marital_status": "Single"
  },
  {
    "time": "2021-05-06T13:02:00.200Z",
    "name": "Alice Johnson",
    "city": "Houston",
    "age": 51,
    "salary": 73797,
    "occupation": "Financial Analyst",
    "marital_status": "Married"
  },
  {
    "time": "2021-05-06T13:02:00.200Z",
    "name": "Michael Lee",
    "city": "Phoenix",
    "age": 48,
    "salary": 70316,
    "occupation": "Graphic Designer",
    "marital_status": "Married"
  },
  {
    "time": "2021-05-06T13:02:00.200Z",
    "name": "Jane Smith",
    "city": "San Francisco",
    "age": 52,
    "salary": 66622,
    "occupation": "Marketing Specialist",
    "marital_status": "Married"
  },
  {
    "time": "2021-05-06T13:02:00.200Z",
    "name": "William Turner",
    "city": "New York",
    "age": 55,
    "salary": 56063,
    "occupation": "CTO",
    "marital_status": "Married"
  },
  {
    "time": "2021-05-06T13:02:00.200Z",
    "name": "Michael Lee",
    "city": "Phoenix",
    "age": 30,
    "salary": 81415,
    "occupation": "CTO",
    "marital_status": "Single"
  },
  {
    "time": "2021-05-06T13:02:00.200Z",
    "name": "Laura Kim",
    "city": "San Francisco",
    "age": 24,
    "salary": 74517,
    "occupation": "UX Designer",
    "marital_status": "Single"
  },
  {
    "time": "2021-05-06T13:02:00.200Z",
    "name": "William Turner",
    "city": "Houston",
    "age": 47,
    "salary": 81505,
    "occupation": "DevOps Engineer",
    "marital_status": "Married"
  },
  {
    "time": "2021-05-06T13:02:00.200Z",
    "name": "Jane Smith",
    "city": "Seattle",
    "age": 41,
    "salary": 51970,
    "occupation": "UX Designer",
    "marital_status": "Married"
  },
  {
    "time": "2021-05-06T13:02:00.200Z",
    "name": "John Doe",
    "city": "Phoenix",
    "age": 30,
    "salary": 77591,
    "occupation": "Financial Analyst",
    "marital_status": "Married"
  },
  {
    "time": "2021-05-06T13:02:00.200Z",
    "name": "William Turner",
    "city": "Los Angeles",
    "age": 28,
    "salary": 75167,
    "occupation": "CTO",
    "marital_status": "Single"
  },
  {
    "time": "2021-05-06T13:02:00.200Z",
    "name": "Alice Johnson",
    "city": "Houston",
    "age": 29,
    "salary": 67744,
    "occupation": "Sales Manager",
    "marital_status": "Single"
  },
  {
    "time": "2021-05-06T13:02:00.200Z",
    "name": "William Turner",
    "city": "Phoenix",
    "age": 51,
    "salary": 82187,
    "occupation": "Financial Analyst",
    "marital_status": "Single"
  },
  {
    "time": "2021-05-06T13:02:00.200Z",
    "name": "John Doe",
    "city": "San Francisco",
    "age": 40,
    "salary": 63107,
    "occupation": "Data Scientist",
    "marital_status": "Married"
  },
  {
    "time": "2021-05-06T13:02:00.200Z",
    "name": "Jane Smith",
    "city": "San Francisco",
    "age": 26,
    "salary": 67568,
    "occupation": "DevOps Engineer",
    "marital_status": "Single"
  },
  {
    "time": "2021-05-06T13:02:00.200Z",
    "name": "John Doe",
    "city": "Chicago",
    "age": 58,
    "salary": 52862,
    "occupation": "Software Engineer",
    "marital_status": "Married"
  },
  {
    "time": "2021-05-06T13:02:00.200Z",
    "name": "William Turner",
    "city": "Denver",
    "age": 52,
    "salary": 57221,
    "occupation": "UX Designer",
    "marital_status": "Married"
  },
  {
    "time": "2021-05-06T13:02:00.200Z",
    "name": "Michael Lee",
    "city": "Houston",
    "age": 37,
    "salary": 73317,
    "occupation": "DevOps Engineer",
    "marital_status": "Married"
  },
  {
    "time": "2021-05-06T13:02:00.200Z",
    "name": "John Doe",
    "city": "Houston",
    "age": 49,
    "salary": 75350,
    "occupation": "Graphic Designer",
    "marital_status": "Married"
  },
  {
    "time": "2021-05-06T13:02:00.200Z",
    "name": "Alice Johnson",
    "city": "Boston",
    "age": 39,
    "salary": 70858,
    "occupation": "Financial Analyst",
    "marital_status": "Single"
  },
  {
    "time": "2021-05-06T13:02:00.200Z",
    "name": "Jane Smith",
    "city": "Seattle",
    "age": 21,
    "salary": 79813,
    "occupation": "Financial Analyst",
    "marital_status": "Married"
  },
  {
    "time": "2021-05-06T13:02:00.200Z",
    "name": "Alice Johnson",
    "city": "Phoenix",
    "age": 59,
    "salary": 51296,
    "occupation": "Data Scientist",
    "marital_status": "Married"
  },
  {
    "time": "2021-05-06T13:02:00.200Z",
    "name": "William Turner",
    "city": "Chicago",
    "age": 49,
    "salary": 55375,
    "occupation": "Software Engineer",
    "marital_status": "Single"
  },
  {
    "time": "2021-05-06T13:02:00.200Z",
    "name": "Michael Lee",
    "city": "Chicago",
    "age": 29,
    "salary": 74271,
    "occupation": "UX Designer",
    "marital_status": "Single"
  },
  {
    "time": "2021-05-06T13:02:00.200Z",
    "name": "John Doe",
    "city": "Denver",
    "age": 30,
    "salary": 77454,
    "occupation": "Graphic Designer",
    "marital_status": "Single"
  },
  {
    "time": "2021-05-06T13:02:00.200Z",
    "name": "Emily Davis",
    "city": "Denver",
    "age": 36,
    "salary": 60966,
    "occupation": "Data Scientist",
    "marital_status": "Single"
  },
  {
    "time": "2021-05-06T13:02:00.200Z",
    "name": "Robert Brown",
    "city": "San Francisco",
    "age": 22,
    "salary": 77057,
    "occupation": "Product Manager",
    "marital_status": "Single"
  },
  {
    "time": "2021-05-06T13:02:00.200Z",
    "name": "Jane Smith",
    "city": "Denver",
    "age": 53,
    "salary": 55140,
    "occupation": "CTO",
    "marital_status": "Single"
  },
  {
    "time": "2021-05-06T13:02:00.200Z",
    "name": "Emily Davis",
    "city": "Phoenix",
    "age": 33,
    "salary": 69774,
    "occupation": "Sales Manager",
    "marital_status": "Married"
  },
  {
    "time": "2021-05-06T13:02:00.200Z",
    "name": "Jane Smith",
    "city": "Houston",
    "age": 20,
    "salary": 53749,
    "occupation": "Data Scientist",
    "marital_status": "Married"
  },
  {
    "time": "2021-05-06T13:02:00.200Z",
    "name": "James Wilson",
    "city": "Los Angeles",
    "age": 33,
    "salary": 55235,
    "occupation": "Sales Manager",
    "marital_status": "Married"
  },
  {
    "time": "2021-05-06T13:02:00.200Z",
    "name": "Emily Davis",
    "city": "Denver",
    "age": 59,
    "salary": 79948,
    "occupation": "DevOps Engineer",
    "marital_status": "Married"
  },
  {
    "time": "2021-05-06T13:02:00.200Z",
    "name": "John Doe",
    "city": "Seattle",
    "age": 45,
    "salary": 55006,
    "occupation": "Product Manager",
    "marital_status": "Married"
  },
  {
    "time": "2021-05-06T13:02:00.200Z",
    "name": "Jane Smith",
    "city": "Chicago",
    "age": 55,
    "salary": 73492,
    "occupation": "UX Designer",
    "marital_status": "Married"
  },
  {
    "time": "2021-05-06T13:02:00.200Z",
    "name": "John Doe",
    "city": "Seattle",
    "age": 39,
    "salary": 52370,
    "occupation": "UX Designer",
    "marital_status": "Single"
  },
  {
    "time": "2021-05-06T13:02:00.200Z",
    "name": "Alice Johnson",
    "city": "Los Angeles",
    "age": 38,
    "salary": 74711,
    "occupation": "Financial Analyst",
    "marital_status": "Single"
  },
  {
    "time": "2021-05-06T13:02:00.200Z",
    "name": "Alice Johnson",
    "city": "Boston",
    "age": 37,
    "salary": 72582,
    "occupation": "Product Manager",
    "marital_status": "Married"
  },
  {
    "time": "2021-05-06T13:02:00.200Z",
    "name": "Michael Lee",
    "city": "Houston",
    "age": 50,
    "salary": 80475,
    "occupation": "Software Engineer",
    "marital_status": "Married"
  },
  {
    "time": "2021-05-06T13:02:00.200Z",
    "name": "Laura Kim",
    "city": "Miami",
    "age": 56,
    "salary": 68765,
    "occupation": "Graphic Designer",
    "marital_status": "Single"
  },
  {
    "time": "2021-05-06T13:02:00.200Z",
    "name": "James Wilson",
    "city": "New York",
    "age": 50,
    "salary": 81103,
    "occupation": "Graphic Designer",
    "marital_status": "Married"
  },
  {
    "time": "2021-05-06T13:02:00.200Z",
    "name": "Alice Johnson",
    "city": "Boston",
    "age": 47,
    "salary": 81399,
    "occupation": "Graphic Designer",
    "marital_status": "Single"
  },
  {
    "time": "2021-05-06T13:02:00.200Z",
    "name": "John Doe",
    "city": "Denver",
    "age": 29,
    "salary": 82601,
    "occupation": "UX Designer",
    "marital_status": "Married"
  },
  {
    "time": "2021-05-06T13:02:00.200Z",
    "name": "John Doe",
    "city": "Denver",
    "age": 49,
    "salary": 74426,
    "occupation": "Product Manager",
    "marital_status": "Married"
  },
  {
    "time": "2021-05-06T13:02:00.200Z",
    "name": "Jane Smith",
    "city": "Phoenix",
    "age": 23,
    "salary": 66124,
    "occupation": "Product Manager",
    "marital_status": "Single"
  },
  {
    "time": "2021-05-06T13:02:00.200Z",
    "name": "James Wilson",
    "city": "Houston",
    "age": 37,
    "salary": 79759,
    "occupation": "DevOps Engineer",
    "marital_status": "Single"
  },
  {
    "time": "2021-05-06T13:02:00.200Z",
    "name": "Jane Smith",
    "city": "Los Angeles",
    "age": 40,
    "salary": 82283,
    "occupation": "Financial Analyst",
    "marital_status": "Single"
  },
  {
    "time": "2021-05-06T13:02:00.200Z",
    "name": "Jane Smith",
    "city": "Boston",
    "age": 50,
    "salary": 53230,
    "occupation": "Data Scientist",
    "marital_status": "Married"
  },
  {
    "time": "2021-05-06T13:02:00.200Z",
    "name": "William Turner",
    "city": "Los Angeles",
    "age": 39,
    "salary": 71728,
    "occupation": "Sales Manager",
    "marital_status": "Married"
  },
  {
    "time": "2021-05-06T13:02:00.200Z",
    "name": "Jane Smith",
    "city": "Denver",
    "age": 23,
    "salary": 73753,
    "occupation": "Product Manager",
    "marital_status": "Married"
  },
  {
    "time": "2021-05-06T13:02:00.200Z",
    "name": "Sophia Martinez",
    "city": "Chicago",
    "age": 34,
    "salary": 68380,
    "occupation": "Software Engineer",
    "marital_status": "Married"
  },
  {
    "time": "2021-05-06T13:02:00.200Z",
    "name": "Jane Smith",
    "city": "Seattle",
    "age": 33,
    "salary": 59369,
    "occupation": "Data Scientist",
    "marital_status": "Single"
  },
  {
    "time": "2021-05-06T13:02:00.200Z",
    "name": "Alice Johnson",
    "city": "Seattle",
    "age": 36,
    "salary": 81836,
    "occupation": "Product Manager",
    "marital_status": "Single"
  },
  {
    "time": "2021-05-06T13:02:00.200Z",
    "name": "Emily Davis",
    "city": "San Francisco",
    "age": 55,
    "salary": 57930,
    "occupation": "Software Engineer",
    "marital_status": "Married"
  },
  {
    "time": "2021-05-06T13:02:00.200Z",
    "name": "Michael Lee",
    "city": "Houston",
    "age": 59,
    "salary": 53183,
    "occupation": "Data Scientist",
    "marital_status": "Married"
  },
  {
    "time": "2021-05-06T13:02:00.200Z",
    "name": "Michael Lee",
    "city": "New York",
    "age": 54,
    "salary": 56711,
    "occupation": "CTO",
    "marital_status": "Single"
  },
  {
    "time": "2021-05-06T13:02:00.200Z",
    "name": "Alice Johnson",
    "city": "San Francisco",
    "age": 39,
    "salary": 65466,
    "occupation": "DevOps Engineer",
    "marital_status": "Married"
  },
  {
    "time": "2021-05-06T13:02:00.200Z",
    "name": "William Turner",
    "city": "San Francisco",
    "age": 44,
    "salary": 73797,
    "occupation": "DevOps Engineer",
    "marital_status": "Single"
  },
  {
    "time": "2021-05-06T13:02:00.200Z",
    "name": "Robert Brown",
    "city": "Chicago",
    "age": 35,
    "salary": 56167,
    "occupation": "Data Scientist",
    "marital_status": "Single"
  },
  {
    "time": "2021-05-06T13:02:00.200Z",
    "name": "William Turner",
    "city": "New York",
    "age": 45,
    "salary": 65360,
    "occupation": "Graphic Designer",
    "marital_status": "Married"
  },
  {
    "time": "2021-05-06T13:02:00.200Z",
    "name": "William Turner",
    "city": "San Francisco",
    "age": 26,
    "salary": 64929,
    "occupation": "Product Manager",
    "marital_status": "Married"
  },
  {
    "time": "2021-05-06T13:02:00.200Z",
    "name": "Michael Lee",
    "city": "San Francisco",
    "age": 55,
    "salary": 51224,
    "occupation": "Marketing Specialist",
    "marital_status": "Married"
  },
  {
    "time": "2021-05-06T13:02:00.200Z",
    "name": "William Turner",
    "city": "Phoenix",
    "age": 41,
    "salary": 67248,
    "occupation": "Graphic Designer",
    "marital_status": "Married"
  },
  {
    "time": "2021-05-06T13:02:00.200Z",
    "name": "Jane Smith",
    "city": "Denver",
    "age": 31,
    "salary": 58361,
    "occupation": "UX Designer",
    "marital_status": "Single"
  },
  {
    "time": "2021-05-06T13:02:00.200Z",
    "name": "Alice Johnson",
    "city": "Chicago",
    "age": 47,
    "salary": 66932,
    "occupation": "UX Designer",
    "marital_status": "Married"
  },
  {
    "time": "2021-05-06T13:02:00.200Z",
    "name": "Sophia Martinez",
    "city": "San Francisco",
    "age": 33,
    "salary": 55357,
    "occupation": "Financial Analyst",
    "marital_status": "Married"
  },
  {
    "time": "2021-05-06T13:02:00.200Z",
    "name": "Michael Lee",
    "city": "Seattle",
    "age": 46,
    "salary": 55107,
    "occupation": "UX Designer",
    "marital_status": "Married"
  },
  {
    "time": "2021-05-06T13:02:00.200Z",
    "name": "John Doe",
    "city": "Seattle",
    "age": 49,
    "salary": 67297,
    "occupation": "UX Designer",
    "marital_status": "Single"
  },
  {
    "time": "2021-05-06T13:02:00.200Z",
    "name": "Sophia Martinez",
    "city": "Boston",
    "age": 30,
    "salary": 82578,
    "occupation": "UX Designer",
    "marital_status": "Single"
  },
  {
    "time": "2021-05-06T13:02:00.200Z",
    "name": "Jane Smith",
    "city": "Seattle",
    "age": 27,
    "salary": 54298,
    "occupation": "CTO",
    "marital_status": "Single"
  },
  {
    "time": "2021-05-06T13:02:00.200Z",
    "name": "Sophia Martinez",
    "city": "San Francisco",
    "age": 31,
    "salary": 53334,
    "occupation": "Marketing Specialist",
    "marital_status": "Single"
  },
  {
    "time": "2021-05-06T13:02:00.200Z",
    "name": "Emily Davis",
    "city": "Houston",
    "age": 43,
    "salary": 70805,
    "occupation": "Marketing Specialist",
    "marital_status": "Single"
  },
  {
    "time": "2021-05-06T13:02:00.200Z",
    "name": "Robert Brown",
    "city": "New York",
    "age": 52,
    "salary": 75815,
    "occupation": "DevOps Engineer",
    "marital_status": "Single"
  },
  {
    "time": "2021-05-06T13:02:00.200Z",
    "name": "Michael Lee",
    "city": "Phoenix",
    "age": 44,
    "salary": 59521,
    "occupation": "Product Manager",
    "marital_status": "Single"
  },
  {
    "time": "2021-05-06T13:02:00.200Z",
    "name": "William Turner",
    "city": "San Francisco",
    "age": 30,
    "salary": 62249,
    "occupation": "Product Manager",
    "marital_status": "Married"
  },
  {
    "time": "2021-05-06T13:02:00.200Z",
    "name": "Sophia Martinez",
    "city": "Seattle",
    "age": 50,
    "salary": 59213,
    "occupation": "CTO",
    "marital_status": "Married"
  },
  {
    "time": "2021-05-06T13:02:00.200Z",
    "name": "Jane Smith",
    "city": "Denver",
    "age": 22,
    "salary": 68010,
    "occupation": "Software Engineer",
    "marital_status": "Married"
  },
  {
    "time": "2021-05-06T13:02:00.200Z",
    "name": "James Wilson",
    "city": "Chicago",
    "age": 23,
    "salary": 81968,
    "occupation": "Financial Analyst",
    "marital_status": "Married"
  },
  {
    "time": "2021-05-06T13:02:00.200Z",
    "name": "Emily Davis",
    "city": "Boston",
    "age": 25,
    "salary": 61322,
    "occupation": "Marketing Specialist",
    "marital_status": "Married"
  },
  {
    "time": "2021-05-06T13:02:00.200Z",
    "name": "Jane Smith",
    "city": "New York",
    "age": 22,
    "salary": 78701,
    "occupation": "Marketing Specialist",
    "marital_status": "Married"
  },
  {
    "time": "2021-05-06T13:02:00.200Z",
    "name": "William Turner",
    "city": "New York",
    "age": 42,
    "salary": 58206,
    "occupation": "Marketing Specialist",
    "marital_status": "Married"
  },
  {
    "time": "2021-05-06T13:02:00.200Z",
    "name": "Michael Lee",
    "city": "Los Angeles",
    "age": 58,
    "salary": 67666,
    "occupation": "Sales Manager",
    "marital_status": "Single"
  },
  {
    "time": "2021-05-06T13:02:00.200Z",
    "name": "Jane Smith",
    "city": "Boston",
    "age": 25,
    "salary": 66642,
    "occupation": "Software Engineer",
    "marital_status": "Single"
  },
  {
    "time": "2021-05-06T13:02:00.200Z",
    "name": "Michael Lee",
    "city": "Los Angeles",
    "age": 37,
    "salary": 58372,
    "occupation": "Product Manager",
    "marital_status": "Single"
  },
  {
    "time": "2021-05-06T13:02:00.200Z",
    "name": "Jane Smith",
    "city": "Seattle",
    "age": 55,
    "salary": 53969,
    "occupation": "DevOps Engineer",
    "marital_status": "Single"
  },
  {
    "time": "2021-05-06T13:02:00.200Z",
    "name": "John Doe",
    "city": "Houston",
    "age": 49,
    "salary": 75005,
    "occupation": "Graphic Designer",
    "marital_status": "Married"
  },
  {
    "time": "2021-05-06T13:02:00.200Z",
    "name": "Michael Lee",
    "city": "Los Angeles",
    "age": 45,
    "salary": 69606,
    "occupation": "CTO",
    "marital_status": "Married"
  },
  {
    "time": "2021-05-06T13:02:00.200Z",
    "name": "Jane Smith",
    "city": "Denver",
    "age": 23,
    "salary": 75600,
    "occupation": "UX Designer",
    "marital_status": "Single"
  },
  {
    "time": "2021-05-06T13:02:00.200Z",
    "name": "Jane Smith",
    "city": "Los Angeles",
    "age": 23,
    "salary": 81760,
    "occupation": "UX Designer",
    "marital_status": "Single"
  },
  {
    "time": "2021-05-06T13:02:00.200Z",
    "name": "Michael Lee",
    "city": "New York",
    "age": 57,
    "salary": 71090,
    "occupation": "Product Manager",
    "marital_status": "Married"
  },
  {
    "time": "2021-05-06T13:02:00.200Z",
    "name": "Michael Lee",
    "city": "New York",
    "age": 45,
    "salary": 53431,
    "occupation": "Marketing Specialist",
    "marital_status": "Married"
  },
  {
    "time": "2021-05-06T13:02:00.200Z",
    "name": "John Doe",
    "city": "New York",
    "age": 48,
    "salary": 76600,
    "occupation": "Product Manager",
    "marital_status": "Single"
  },
  {
    "time": "2021-05-06T13:02:00.200Z",
    "name": "Sophia Martinez",
    "city": "Boston",
    "age": 20,
    "salary": 78512,
    "occupation": "Marketing Specialist",
    "marital_status": "Single"
  },
  {
    "time": "2021-05-06T13:02:00.200Z",
    "name": "Jane Smith",
    "city": "Seattle",
    "age": 29,
    "salary": 68064,
    "occupation": "Graphic Designer",
    "marital_status": "Married"
  },
  {
    "time": "2021-05-06T13:02:00.200Z",
    "name": "Jane Smith",
    "city": "San Francisco",
    "age": 31,
    "salary": 54722,
    "occupation": "CTO",
    "marital_status": "Single"
  },
  {
    "time": "2021-05-06T13:02:00.200Z",
    "name": "Michael Lee",
    "city": "Seattle",
    "age": 41,
    "salary": 68048,
    "occupation": "Product Manager",
    "marital_status": "Married"
  },
  {
    "time": "2021-05-06T13:02:00.200Z",
    "name": "James Wilson",
    "city": "Chicago",
    "age": 57,
    "salary": 57654,
    "occupation": "Sales Manager",
    "marital_status": "Single"
  },
  {
    "time": "2021-05-06T13:02:00.200Z",
    "name": "Jane Smith",
    "city": "New York",
    "age": 28,
    "salary": 75105,
    "occupation": "Graphic Designer",
    "marital_status": "Single"
  },
  {
    "time": "2021-05-06T13:02:00.200Z",
    "name": "William Turner",
    "city": "Phoenix",
    "age": 22,
    "salary": 73489,
    "occupation": "Marketing Specialist",
    "marital_status": "Married"
  },
  {
    "time": "2021-05-06T13:02:00.200Z",
    "name": "Laura Kim",
    "city": "Phoenix",
    "age": 30,
    "salary": 58841,
    "occupation": "DevOps Engineer",
    "marital_status": "Single"
  },
  {
    "time": "2021-05-06T13:02:00.200Z",
    "name": "John Doe",
    "city": "Denver",
    "age": 52,
    "salary": 58033,
    "occupation": "Product Manager",
    "marital_status": "Married"
  },
  {
    "time": "2021-05-06T13:02:00.200Z",
    "name": "William Turner",
    "city": "Chicago",
    "age": 57,
    "salary": 62715,
    "occupation": "Graphic Designer",
    "marital_status": "Single"
  },
  {
    "time": "2021-05-06T13:02:00.200Z",
    "name": "William Turner",
    "city": "Boston",
    "age": 21,
    "salary": 60984,
    "occupation": "Marketing Specialist",
    "marital_status": "Single"
  },
  {
    "time": "2021-05-06T13:02:00.200Z",
    "name": "Emily Davis",
    "city": "Denver",
    "age": 41,
    "salary": 79679,
    "occupation": "Data Scientist",
    "marital_status": "Single"
  },
  {
    "time": "2021-05-06T13:02:00.200Z",
    "name": "John Doe",
    "city": "San Francisco",
    "age": 35,
    "salary": 72363,
    "occupation": "Software Engineer",
    "marital_status": "Single"
  },
  {
    "time": "2021-05-06T13:02:00.200Z",
    "name": "James Wilson",
    "city": "Los Angeles",
    "age": 49,
    "salary": 70368,
    "occupation": "Graphic Designer",
    "marital_status": "Single"
  },
  {
    "time": "2021-05-06T13:02:00.200Z",
    "name": "Robert Brown",
    "city": "Miami",
    "age": 32,
    "salary": 50904,
    "occupation": "DevOps Engineer",
    "marital_status": "Married"
  },
  {
    "time": "2021-05-06T13:02:00.200Z",
    "name": "Robert Brown",
    "city": "Phoenix",
    "age": 22,
    "salary": 51097,
    "occupation": "Software Engineer",
    "marital_status": "Single"
  },
  {
    "time": "2021-05-06T13:02:00.200Z",
    "name": "Laura Kim",
    "city": "Boston",
    "age": 43,
    "salary": 53499,
    "occupation": "DevOps Engineer",
    "marital_status": "Married"
  },
  {
    "time": "2021-05-06T13:02:00.200Z",
    "name": "Laura Kim",
    "city": "Miami",
    "age": 33,
    "salary": 64302,
    "occupation": "Software Engineer",
    "marital_status": "Married"
  },
  {
    "time": "2021-05-06T13:02:00.200Z",
    "name": "Laura Kim",
    "city": "Denver",
    "age": 52,
    "salary": 73504,
    "occupation": "Sales Manager",
    "marital_status": "Single"
  },
  {
    "time": "2021-05-06T13:02:00.200Z",
    "name": "Michael Lee",
    "city": "Boston",
    "age": 22,
    "salary": 57004,
    "occupation": "Financial Analyst",
    "marital_status": "Single"
  },
  {
    "time": "2021-05-06T13:02:00.200Z",
    "name": "Jane Smith",
    "city": "Miami",
    "age": 26,
    "salary": 64070,
    "occupation": "Financial Analyst",
    "marital_status": "Single"
  },
  {
    "time": "2021-05-06T13:02:00.200Z",
    "name": "Emily Davis",
    "city": "Denver",
    "age": 21,
    "salary": 69744,
    "occupation": "DevOps Engineer",
    "marital_status": "Single"
  },
  {
    "time": "2021-05-06T13:02:00.200Z",
    "name": "Emily Davis",
    "city": "San Francisco",
    "age": 50,
    "salary": 81991,
    "occupation": "Marketing Specialist",
    "marital_status": "Single"
  },
  {
    "time": "2021-05-06T13:02:00.200Z",
    "name": "Michael Lee",
    "city": "New York",
    "age": 21,
    "salary": 73449,
    "occupation": "Marketing Specialist",
    "marital_status": "Single"
  },
  {
    "time": "2021-05-06T13:02:00.200Z",
    "name": "Sophia Martinez",
    "city": "Houston",
    "age": 47,
    "salary": 77945,
    "occupation": "Financial Analyst",
    "marital_status": "Married"
  },
  {
    "time": "2021-05-06T13:02:00.200Z",
    "name": "William Turner",
    "city": "Boston",
    "age": 58,
    "salary": 53276,
    "occupation": "Financial Analyst",
    "marital_status": "Married"
  },
  {
    "time": "2021-05-06T13:02:00.200Z",
    "name": "Michael Lee",
    "city": "Los Angeles",
    "age": 24,
    "salary": 55059,
    "occupation": "Data Scientist",
    "marital_status": "Married"
  },
  {
    "time": "2021-05-06T13:02:00.200Z",
    "name": "Michael Lee",
    "city": "Seattle",
    "age": 59,
    "salary": 70122,
    "occupation": "UX Designer",
    "marital_status": "Single"
  },
  {
    "time": "2021-05-06T13:02:00.200Z",
    "name": "Emily Davis",
    "city": "Denver",
    "age": 53,
    "salary": 56144,
    "occupation": "Financial Analyst",
    "marital_status": "Single"
  },
  {
    "time": "2021-05-06T13:02:00.200Z",
    "name": "Laura Kim",
    "city": "New York",
    "age": 38,
    "salary": 79635,
    "occupation": "Marketing Specialist",
    "marital_status": "Married"
  },
  {
    "time": "2021-05-06T13:02:00.200Z",
    "name": "Jane Smith",
    "city": "Phoenix",
    "age": 56,
    "salary": 78933,
    "occupation": "CTO",
    "marital_status": "Married"
  },
  {
    "time": "2021-05-06T13:02:00.200Z",
    "name": "John Doe",
    "city": "Denver",
    "age": 54,
    "salary": 58617,
    "occupation": "Sales Manager",
    "marital_status": "Married"
  },
  {
    "time": "2021-05-06T13:02:00.200Z",
    "name": "James Wilson",
    "city": "Boston",
    "age": 52,
    "salary": 67795,
    "occupation": "CTO",
    "marital_status": "Single"
  },
  {
    "time": "2021-05-06T13:02:00.200Z",
    "name": "Alice Johnson",
    "city": "Seattle",
    "age": 50,
    "salary": 54820,
    "occupation": "UX Designer",
    "marital_status": "Single"
  },
  {
    "time": "2021-05-06T13:02:00.200Z",
    "name": "Jane Smith",
    "city": "Miami",
    "age": 39,
    "salary": 81259,
    "occupation": "Graphic Designer",
    "marital_status": "Married"
  },
  {
    "time": "2021-05-06T13:02:00.200Z",
    "name": "James Wilson",
    "city": "Los Angeles",
    "age": 22,
    "salary": 54665,
    "occupation": "Software Engineer",
    "marital_status": "Married"
  },
  {
    "time": "2021-05-06T13:02:00.200Z",
    "name": "Laura Kim",
    "city": "San Francisco",
    "age": 32,
    "salary": 62932,
    "occupation": "Graphic Designer",
    "marital_status": "Married"
  },
  {
    "time": "2021-05-06T13:02:00.200Z",
    "name": "Laura Kim",
    "city": "Miami",
    "age": 39,
    "salary": 71305,
    "occupation": "Sales Manager",
    "marital_status": "Married"
  },
  {
    "time": "2021-05-06T13:02:00.200Z",
    "name": "Laura Kim",
    "city": "Phoenix",
    "age": 31,
    "salary": 68797,
    "occupation": "UX Designer",
    "marital_status": "Married"
  },
  {
    "time": "2021-05-06T13:02:00.200Z",
    "name": "Laura Kim",
    "city": "Denver",
    "age": 24,
    "salary": 52666,
    "occupation": "Software Engineer",
    "marital_status": "Married"
  },
  {
    "time": "2021-05-06T13:02:00.200Z",
    "name": "Laura Kim",
    "city": "Denver",
    "age": 32,
    "salary": 50802,
    "occupation": "Product Manager",
    "marital_status": "Single"
  },
  {
    "time": "2021-05-06T13:02:00.200Z",
    "name": "James Wilson",
    "city": "Houston",
    "age": 54,
    "salary": 77416,
    "occupation": "CTO",
    "marital_status": "Married"
  },
  {
    "time": "2021-05-06T13:02:00.200Z",
    "name": "Alice Johnson",
    "city": "Boston",
    "age": 54,
    "salary": 82496,
    "occupation": "Software Engineer",
    "marital_status": "Married"
  },
  {
    "time": "2021-05-06T13:02:00.200Z",
    "name": "Alice Johnson",
    "city": "Los Angeles",
    "age": 20,
    "salary": 78041,
    "occupation": "Graphic Designer",
    "marital_status": "Married"
  },
  {
    "time": "2021-05-06T13:02:00.200Z",
    "name": "John Doe",
    "city": "San Francisco",
    "age": 23,
    "salary": 61081,
    "occupation": "DevOps Engineer",
    "marital_status": "Single"
  },
  {
    "time": "2021-05-06T13:02:00.200Z",
    "name": "William Turner",
    "city": "New York",
    "age": 22,
    "salary": 50515,
    "occupation": "Sales Manager",
    "marital_status": "Married"
  },
  {
    "time": "2021-05-06T13:02:00.200Z",
    "name": "Sophia Martinez",
    "city": "Boston",
    "age": 29,
    "salary": 66550,
    "occupation": "DevOps Engineer",
    "marital_status": "Married"
  },
  {
    "time": "2021-05-06T13:02:00.200Z",
    "name": "Jane Smith",
    "city": "Seattle",
    "age": 23,
    "salary": 55262,
    "occupation": "UX Designer",
    "marital_status": "Single"
  },
  {
    "time": "2021-05-06T13:02:00.200Z",
    "name": "Sophia Martinez",
    "city": "Chicago",
    "age": 22,
    "salary": 51839,
    "occupation": "DevOps Engineer",
    "marital_status": "Married"
  },
  {
    "time": "2021-05-06T13:02:00.200Z",
    "name": "James Wilson",
    "city": "Boston",
    "age": 42,
    "salary": 51401,
    "occupation": "Data Scientist",
    "marital_status": "Married"
  },
  {
    "time": "2021-05-06T13:02:00.200Z",
    "name": "Michael Lee",
    "city": "San Francisco",
    "age": 57,
    "salary": 77420,
    "occupation": "Marketing Specialist",
    "marital_status": "Single"
  },
  {
    "time": "2021-05-06T13:02:00.200Z",
    "name": "Laura Kim",
    "city": "Boston",
    "age": 41,
    "salary": 81389,
    "occupation": "Marketing Specialist",
    "marital_status": "Married"
  },
  {
    "time": "2021-05-06T13:02:00.200Z",
    "name": "Jane Smith",
    "city": "Houston",
    "age": 49,
    "salary": 59176,
    "occupation": "Software Engineer",
    "marital_status": "Married"
  },
  {
    "time": "2021-05-06T13:02:00.200Z",
    "name": "Robert Brown",
    "city": "Chicago",
    "age": 40,
    "salary": 61619,
    "occupation": "UX Designer",
    "marital_status": "Married"
  },
  {
    "time": "2021-05-06T13:02:00.200Z",
    "name": "Emily Davis",
    "city": "Phoenix",
    "age": 21,
    "salary": 79162,
    "occupation": "Financial Analyst",
    "marital_status": "Single"
  },
  {
    "time": "2021-05-06T13:02:00.200Z",
    "name": "Michael Lee",
    "city": "Phoenix",
    "age": 48,
    "salary": 56534,
    "occupation": "Graphic Designer",
    "marital_status": "Single"
  },
  {
    "time": "2021-05-06T13:02:00.200Z",
    "name": "Laura Kim",
    "city": "Seattle",
    "age": 38,
    "salary": 64228,
    "occupation": "CTO",
    "marital_status": "Married"
  },
  {
    "time": "2021-05-06T13:02:00.200Z",
    "name": "Michael Lee",
    "city": "Seattle",
    "age": 27,
    "salary": 62439,
    "occupation": "Data Scientist",
    "marital_status": "Married"
  },
  {
    "time": "2021-05-06T13:02:00.200Z",
    "name": "Michael Lee",
    "city": "Miami",
    "age": 46,
    "salary": 78727,
    "occupation": "Financial Analyst",
    "marital_status": "Married"
  },
  {
    "time": "2021-05-06T13:02:00.200Z",
    "name": "Alice Johnson",
    "city": "New York",
    "age": 27,
    "salary": 80277,
    "occupation": "Product Manager",
    "marital_status": "Single"
  },
  {
    "time": "2021-05-06T13:02:00.200Z",
    "name": "Alice Johnson",
    "city": "Miami",
    "age": 41,
    "salary": 69068,
    "occupation": "DevOps Engineer",
    "marital_status": "Married"
  },
  {
    "time": "2021-05-06T13:02:00.200Z",
    "name": "Emily Davis",
    "city": "San Francisco",
    "age": 50,
    "salary": 60585,
    "occupation": "UX Designer",
    "marital_status": "Married"
  },
  {
    "time": "2021-05-06T13:02:00.200Z",
    "name": "Michael Lee",
    "city": "Houston",
    "age": 37,
    "salary": 76931,
    "occupation": "DevOps Engineer",
    "marital_status": "Single"
  },
  {
    "time": "2021-05-06T13:02:00.200Z",
    "name": "Alice Johnson",
    "city": "Phoenix",
    "age": 40,
    "salary": 73938,
    "occupation": "Sales Manager",
    "marital_status": "Single"
  },
  {
    "time": "2021-05-06T13:02:00.200Z",
    "name": "John Doe",
    "city": "Seattle",
    "age": 34,
    "salary": 53832,
    "occupation": "Financial Analyst",
    "marital_status": "Married"
  },
  {
    "time": "2021-05-06T13:02:00.200Z",
    "name": "Jane Smith",
    "city": "Miami",
    "age": 48,
    "salary": 60709,
    "occupation": "Marketing Specialist",
    "marital_status": "Single"
  },
  {
    "time": "2021-05-06T13:02:00.200Z",
    "name": "Sophia Martinez",
    "city": "Denver",
    "age": 25,
    "salary": 64490,
    "occupation": "Sales Manager",
    "marital_status": "Single"
  },
  {
    "time": "2021-05-06T13:02:00.200Z",
    "name": "Alice Johnson",
    "city": "Phoenix",
    "age": 39,
    "salary": 70497,
    "occupation": "Sales Manager",
    "marital_status": "Single"
  },
  {
    "time": "2021-05-06T13:02:00.200Z",
    "name": "William Turner",
    "city": "New York",
    "age": 37,
    "salary": 77196,
    "occupation": "Graphic Designer",
    "marital_status": "Married"
  },
  {
    "time": "2021-05-06T13:02:00.200Z",
    "name": "Michael Lee",
    "city": "Boston",
    "age": 26,
    "salary": 50166,
    "occupation": "Software Engineer",
    "marital_status": "Married"
  },
  {
    "time": "2021-05-06T13:02:00.200Z",
    "name": "Laura Kim",
    "city": "San Francisco",
    "age": 43,
    "salary": 63112,
    "occupation": "Product Manager",
    "marital_status": "Single"
  },
  {
    "time": "2021-05-06T13:02:00.200Z",
    "name": "John Doe",
    "city": "New York",
    "age": 37,
    "salary": 58051,
    "occupation": "Financial Analyst",
    "marital_status": "Single"
  },
  {
    "time": "2021-05-06T13:02:00.200Z",
    "name": "Michael Lee",
    "city": "Boston",
    "age": 57,
    "salary": 61462,
    "occupation": "Marketing Specialist",
    "marital_status": "Single"
  },
  {
    "time": "2021-05-06T13:02:00.200Z",
    "name": "Jane Smith",
    "city": "Chicago",
    "age": 51,
    "salary": 61602,
    "occupation": "DevOps Engineer",
    "marital_status": "Married"
  },
  {
    "time": "2021-05-06T13:02:00.200Z",
    "name": "Jane Smith",
    "city": "Denver",
    "age": 40,
    "salary": 80559,
    "occupation": "Financial Analyst",
    "marital_status": "Single"
  },
  {
    "time": "2021-05-06T13:02:00.200Z",
    "name": "Jane Smith",
    "city": "Miami",
    "age": 34,
    "salary": 64932,
    "occupation": "Software Engineer",
    "marital_status": "Single"
  },
  {
    "time": "2021-05-06T13:02:00.200Z",
    "name": "James Wilson",
    "city": "Chicago",
    "age": 42,
    "salary": 81458,
    "occupation": "Data Scientist",
    "marital_status": "Married"
  },
  {
    "time": "2021-05-06T13:02:00.200Z",
    "name": "Michael Lee",
    "city": "Phoenix",
    "age": 27,
    "salary": 51227,
    "occupation": "Graphic Designer",
    "marital_status": "Married"
  },
  {
    "time": "2021-05-06T13:02:00.200Z",
    "name": "William Turner",
    "city": "Denver",
    "age": 35,
    "salary": 78019,
    "occupation": "Product Manager",
    "marital_status": "Married"
  },
  {
    "time": "2021-05-06T13:02:00.200Z",
    "name": "John Doe",
    "city": "Seattle",
    "age": 51,
    "salary": 60508,
    "occupation": "Sales Manager",
    "marital_status": "Single"
  },
  {
    "time": "2021-05-06T13:02:00.200Z",
    "name": "Emily Davis",
    "city": "Miami",
    "age": 55,
    "salary": 75894,
    "occupation": "CTO",
    "marital_status": "Single"
  },
  {
    "time": "2021-05-06T13:02:00.200Z",
    "name": "Sophia Martinez",
    "city": "Houston",
    "age": 51,
    "salary": 51520,
    "occupation": "UX Designer",
    "marital_status": "Single"
  },
  {
    "time": "2021-05-06T13:02:00.200Z",
    "name": "Michael Lee",
    "city": "New York",
    "age": 32,
    "salary": 80815,
    "occupation": "UX Designer",
    "marital_status": "Single"
  },
  {
    "time": "2021-05-06T13:02:00.200Z",
    "name": "Alice Johnson",
    "city": "New York",
    "age": 40,
    "salary": 64878,
    "occupation": "Product Manager",
    "marital_status": "Married"
  },
  {
    "time": "2021-05-06T13:02:00.200Z",
    "name": "Robert Brown",
    "city": "Los Angeles",
    "age": 29,
    "salary": 62534,
    "occupation": "Software Engineer",
    "marital_status": "Single"
  },
  {
    "time": "2021-05-06T13:02:00.200Z",
    "name": "John Doe",
    "city": "Miami",
    "age": 59,
    "salary": 74074,
    "occupation": "Product Manager",
    "marital_status": "Married"
  },
  {
    "time": "2021-05-06T13:02:00.200Z",
    "name": "Robert Brown",
    "city": "Phoenix",
    "age": 57,
    "salary": 72045,
    "occupation": "Data Scientist",
    "marital_status": "Married"
  },
  {
    "time": "2021-05-06T13:02:00.200Z",
    "name": "William Turner",
    "city": "Phoenix",
    "age": 47,
    "salary": 74251,
    "occupation": "Financial Analyst",
    "marital_status": "Married"
  },
  {
    "time": "2021-05-06T13:02:00.200Z",
    "name": "Michael Lee",
    "city": "Seattle",
    "age": 50,
    "salary": 70737,
    "occupation": "Sales Manager",
    "marital_status": "Married"
  }
]
